CHANGES.rst
MANIFEST.in
README.rst
setup.py
django_rss_plugin.egg-info/PKG-INFO
django_rss_plugin.egg-info/SOURCES.txt
django_rss_plugin.egg-info/dependency_links.txt
django_rss_plugin.egg-info/not-zip-safe
django_rss_plugin.egg-info/requires.txt
django_rss_plugin.egg-info/top_level.txt
rssplugin/__init__.py
rssplugin/cms_plugins.py
rssplugin/models.py
rssplugin/tests.py
rssplugin/utils.py
rssplugin/views.py
rssplugin/migrations/0001_initial.py
rssplugin/migrations/0002_auto__chg_field_rssplugin_rss_url.py
rssplugin/migrations/0003_fix_table_names.py
rssplugin/migrations/__init__.py
rssplugin/templates/rss/rss.html
rssplugin/templatetags/__init__.py
rssplugin/templatetags/rss_tags.py