Metadata-Version: 1.1
Name: django-rss-plugin
Version: 0.1.0
Summary: A Django CMS plugin to show a list of feeds.
Home-page: http://github.com/zgwmike/django-rss-plugin
Author: Guangwen Zhou
Author-email: zgwmike@hotmail.com
License: BSD
Keywords: django cms plugin django-rss-plugin
Platform: UNKNOWN
Classifier: Development Status :: 5 - Production/Stable
Classifier: Environment :: Plugins
Classifier: Environment :: Web Environment
Classifier: Framework :: Django
Classifier: Intended Audience :: Developers
Classifier: License :: OSI Approved :: BSD License
Classifier: Natural Language :: English
Classifier: Operating System :: OS Independent
Classifier: Programming Language :: Python :: 2
Classifier: Topic :: Multimedia :: Video :: Display
Classifier: Topic :: Software Development :: Libraries :: Python Modules
Classifier: Topic :: Utilities
